compare.v
module compare(clk,rst,a,b,out);
input clk;
input rst;
input [31:0] a;
input [31:0] b;
output [31:0] out; //返回(a > b) ? 3f800000 : 

reg [7:0] pow_a;
reg [7:0] pow_b;
reg [22:0] val_a;
reg [22:0] val_b;
reg flag_a;
reg flag_b;
reg flag_same,flag_big,flag_small;
reg [31:0] out_reg;

always @(*) begin
	pow_a = a[30:23];
	pow_b = b[30:23];
	val_a = a[22:0];
	val_b = b[22:0];
	flag_a = a[31];
	flag_b = b[31];
	flag_same = (flag_a == flag_b ) ? 1'b1 : 1'b0;
	flag_big = ((flag_a == 1'b0 )&(flag_b == 1'b1)) ? 1'b1 : 1'b0;
	flag_small = ((flag_a == 1'b1 )&(flag_b == 1'b0)) ? 1'b1 : 1'b0;
	if (flag_big) out_reg = 32'h3f800000;
	if (flag_small) out_reg = 32'h33d6bf95;
	if (flag_same) begin
	
	if (pow_a == pow_b) begin
	if (val_a == val_b) out_reg = 32'h33d6bf95;
	else if(val_a > val_b) begin
		out_reg = flag_a ? 32'h33d6bf95 : 32'h3f800000;
	end
	else begin
		out_reg = flag_a ? 32'h3f800000 : 32'h33d6bf95;
	end
	end
	
	else if(pow_a > pow_b) begin
		out_reg = flag_a ? 32'h33d6bf95 : 32'h3f800000;
	end
	
	else begin
		out_reg = flag_a ? 32'h3f800000 : 32'h33d6bf95;
	end
	
	end
end

assign out = out_reg;
endmodule

tb.v
`timescale 1ns/1ns

module tb();

reg clk;
initial clk=0;
always #1 clk = ~clk;

reg [31:0] rnd1mem [0:999];
reg [31:0] rnd2mem [0:999];

reg [10:0]addr;

wire [31:0] out;
wire [31:0] a,b;
integer file1;
initial begin
       $readmemh("E:/CASIA/SNN_RL-co/code_part/verification_compare/rnd1hex.txt",rnd1mem);
		 $readmemh("E:/CASIA/SNN_RL-co/code_part/verification_compare/rnd2hex.txt",rnd2mem);
		 file1 = $fopen("E:/CASIA/SNN_RL-co/code_part/verification_compare/compare.txt","w");
		 addr=0;


end

initial
        begin            
            $dumpfile("tb.vcd");
            $dumpvars(0,tb);
        end

always@(posedge clk)
begin
	$fwrite(file1,"%h\n",out);
	addr = addr + 1;
	if (addr > 999) begin
		$fclose(file1);
		$stop;
	end
end
assign a =rnd1mem[addr];
assign b =rnd2mem[addr];

compare c1(clk,rst,a,b,out);
endmodule

tb.vcd
$date
	Fri Aug 20 11:58:46 2021
$end
$version
	Icarus Verilog
$end
$timescale
	1ns
$end
$scope module tb $end
$var wire 32 ! a [31:0] $end
$var wire 32 " b [31:0] $end
$var wire 1 # rst $end
$var wire 32 $ out [31:0] $end
$var reg 11 % addr [10:0] $end
$var reg 1 & clk $end
$var integer 32 ' file1 [31:0] $end
$scope module c1 $end
$var wire 32 ( a [31:0] $end
$var wire 32 ) b [31:0] $end
$var wire 1 & clk $end
$var wire 32 * out [31:0] $end
$var wire 1 # rst $end
$var reg 1 + flag_a $end
$var reg 1 , flag_b $end
$var reg 1 - flag_big $end
$var reg 1 . flag_same $end
$var reg 1 / flag_small $end
$var reg 32 0 out_reg [31:0] $end
$var reg 8 1 pow_a [7:0] $end
$var reg 8 2 pow_b [7:0] $end
$var reg 23 3 val_a [22:0] $end
$var reg 23 4 val_b [22:0] $end
$upscope $end
$upscope $end
$enddefinitions $end
#0
$dumpvars
b11110110111000011 4
b100100110001111011100 3
b10000010 2
b10000010 1
b111111100000000000000000000000 0
0/
0.
1-
1,
0+
b111111100000000000000000000000 *
b11000001000000011110110111000011 )
b1000001000100100110001111011100 (
b10000000000000000000000000000011 '
0&
b0 %
b111111100000000000000000000000 $
z#
b11000001000000011110110111000011 "
b1000001000100100110001111011100 !
$end
#1
0-
1.
0,
b11100011011000000111010 4
b1111110111100011011 3
b10000001 2
b1000001000001111110111100011011 !
b1000001000001111110111100011011 (
b1000000111100011011000000111010 "
b1000000111100011011000000111010 )
b1 %
1&
#2
0&
#3
1-
0.
1,
b11011100101011111111110 4
b100000110100001101010 3
b10000001 1
b1000000100100000110100001101010 !
b1000000100100000110100001101010 (
b11000000111011100101011111111110 "
b11000000111011100101011111111110 )
b10 %
1&
#4
0&
#5
b110011110101101011111110010101 $
b110011110101101011111110010101 *
b110011110101101011111110010101 0
1/
0-
0,
1+
b110110110111110010100 4
b1011111101101001101 3
b10000010 2
b10000010 1
b11000001000001011111101101001101 !
b11000001000001011111101101001101 (
b1000001000110110110111110010100 "
b1000001000110110110111110010100 )
b11 %
1&
#6
0&
#7
b111111100000000000000000000000 $
b111111100000000000000000000000 *
b111111100000000000000000000000 0
0/
1.
1,
b1100100011101101101101 4
b1011111011100100111101 3
b10000000 2
b10000000 1
b11000000001011111011100100111101 !
b11000000001011111011100100111101 (
b11000000001100100011101101101101 "
b11000000001100100011101101101101 )
b100 %
1&
#8
0&
#9
b110011110101101011111110010101 $
b110011110101101011111110010101 *
b110011110101101011111110010101 0
b11101001111010000000 4
b111011101111101111 3
b10000001 1
b11000000100000111011101111101111 !
b11000000100000111011101111101111 (
b11000000000011101001111010000000 "
b11000000000011101001111010000000 )
b101 %
1&
#10
0&
#11
b11011010100110101100110 4
b11000001010110110100 3
b10000001 2
b10000010 1
b11000001000011000001010110110100 !
b11000001000011000001010110110100 (
b11000000111011010100110101100110 "
b11000000111011010100110101100110 )
b110 %
1&
#12
0&
#13
1/
0.
0,
b11010010000011001101100 4
b100001001100111110110 3
b10000000 2
b10000001 1
b11000000100100001001100111110110 !
b11000000100100001001100111110110 (
b1000000011010010000011001101100 "
b1000000011010010000011001101100 )
b111 %
1&
#14
0&
#15
b111111100000000000000000000000 $
b111111100000000000000000000000 *
b111111100000000000000000000000 0
0/
1.
0+
b1110101001000110000110 4
b110101100101100010110 3
b1111111 2
b10000010 1
b1000001000110101100101100010110 !
b1000001000110101100101100010110 (
b111111101110101001000110000110 "
b111111101110101001000110000110 )
b1000 %
1&
#16
0&
#17
b110011110101101011111110010101 $
b110011110101101011111110010101 *
b110011110101101011111110010101 0
1/
0.
1+
b1101111000101000101011 4
b101000111110101110 3
b11000001000000101000111110101110 !
b11000001000000101000111110101110 (
b111111101101111000101000101011 "
b111111101101111000101000101011 )
b1001 %
1&
#18
0&
#19
0/
1.
1,
b11110101111100110110101 4
b100001000000111110001 3
b10000001 2
b11000001000100001000000111110001 !
b11000001000100001000000111110001 (
b11000000111110101111100110110101 "
b11000000111110101111100110110101 )
b1010 %
1&
#20
0&
#21
b111111100000000000000000000000 $
b111111100000000000000000000000 *
b111111100000000000000000000000 0
0,
0+
b10000001000111110000110 4
b11100110110111010000111 3
b1111111 2
b10000001 1
b1000000111100110110111010000111 !
b1000000111100110110111010000111 (
b111111110000001000111110000110 "
b111111110000001000111110000110 )
b1011 %
1&
#22
0&
#23
b110011110101101011111110010101 $
b110011110101101011111110010101 *
b110011110101101011111110010101 0
1/
0.
1+
b1000010001000101011 4
b1100100001000101011110 3
b10000010 2
b10000000 1
b11000000001100100001000101011110 !
b11000000001100100001000101011110 (
b1000001000001000010001000101011 "
b1000001000001000010001000101011 )
b1100 %
1&
#24
0&
#25
0/
1.
0+
b111000111010000111100 4
b110001001111111111010 3
b10000010 1
b1000001000110001001111111111010 !
b1000001000110001001111111111010 (
b1000001000111000111010000111100 "
b1000001000111000111010000111100 )
b1101 %
1&
#26
0&
#27
1/
0.
1+
b101111100001011011101 4
b110000100011111100000 3
b11000001000110000100011111100000 !
b11000001000110000100011111100000 (
b1000001000101111100001011011101 "
b1000001000101111100001011011101 )
b1110 %
1&
#28
0&
#29
b111111100000000000000000000000 $
b111111100000000000000000000000 *
b111111100000000000000000000000 0
0/
1-
1,
0+
b11100001100010100100000 4
b11110100000111011100011 3
b10000001 2
b10000001 1
b1000000111110100000111011100011 !
b1000000111110100000111011100011 (
b11000000111100001100010100100000 "
b11000000111100001100010100100000 )
b1111 %
1&
#30
0&
#31
b110011110101101011111110010101 $
b110011110101101011111110010101 *
b110011110101101011111110010101 0
1/
0-
0,
1+
b101000101011101100000 4
b110001000000011110001 3
b11000000100110001000000011110001 !
b11000000100110001000000011110001 (
b1000000100101000101011101100000 "
b1000000100101000101011101100000 )
b10000 %
1&
#32
0&
#33
b1111001111000011000111 4
b11011011110010111000101 3
b11000000111011011110010111000101 !
b11000000111011011110010111000101 (
b1000000101111001111000011000111 "
b1000000101111001111000011000111 )
b10001 %
1&
#34
0&
#35
b111111100000000000000000000000 $
b111111100000000000000000000000 *
b111111100000000000000000000000 0
0/
1-
1,
0+
b10010101001110001111000 4
b1110110100010100001111 3
b1111111 1
b111111101110110100010100001111 !
b111111101110110100010100001111 (
b11000000110010101001110001111000 "
b11000000110010101001110001111000 )
b10010 %
1&
#36
0&
#37
b110011110101101011111110010101 $
b110011110101101011111110010101 *
b110011110101101011111110010101 0
0-
1.
0,
b1111000010001000111110 4
b10011100001101111001010 3
b10000000 2
b111111110011100001101111001010 !
b111111110011100001101111001010 (
b1000000001111000010001000111110 "
b1000000001111000010001000111110 )
b10011 %
1&
#38
0&
#39
1/
0.
1+
b10100000000101011000 4
b10110101010111111100 3
b1111111 2
b10000010 1
b11000001000010110101010111111100 !
b11000001000010110101010111111100 (
b111111100010100000000101011000 "
b111111100010100000000101011000 )
b10100 %
1&
#40
0&
#41
b111111100000000000000000000000 $
b111111100000000000000000000000 *
b111111100000000000000000000000 0
0/
1.
1,
b11010111000111011100101 4
b1101010001110000100010 3
b10000001 2
b1111111 1
b10111111101101010001110000100010 !
b10111111101101010001110000100010 (
b11000000111010111000111011100101 "
b11000000111010111000111011100101 )
b10101 %
1&
#42
0&
#43
1-
0.
0+
b11011011110001011110011 4
b100111101110000000001 3
b10000000 2
b10000001 1
b1000000100100111101110000000001 !
b1000000100100111101110000000001 (
b11000000011011011110001011110011 "
b11000000011011011110001011110011 )
b10110 %
1&
#44
0&
#45
0-
1.
0,
b11100011010101001100001 4
b11110110101100101001111 3
b1111110 2
b1111111 1
b111111111110110101100101001111 !
b111111111110110101100101001111 (
b111111011100011010101001100001 "
b111111011100011010101001100001 )
b10111 %
1&
#46
0&
#47
b110011110101101011111110010101 $
b110011110101101011111110010101 *
b110011110101101011111110010101 0
1/
0.
1+
b11000001011111111100 4
b110010000100001001001 3
b1111111 2
b10000010 1
b11000001000110010000100001001001 !
b11000001000110010000100001001001 (
b111111100011000001011111111100 "
b111111100011000001011111111100 )
b11000 %
1&
#48
0&
#49
b100000110100111101000 4
b111101110111000001011 3
b10000000 2
b11000001000111101110111000001011 !
b11000001000111101110111000001011 (
b1000000000100000110100111101000 "
b1000000000100000110100111101000 )
b11001 %
1&
#50
0&
#51
b111111100000000000000000000000 $
b111111100000000000000000000000 *
b111111100000000000000000000000 0
0/
1.
1,
b101001000000011100000 4
b1100000010110000001010 3
b1111110 1
b10111111001100000010110000001010 !
b10111111001100000010110000001010 (
b11000000000101001000000011100000 "
b11000000000101001000000011100000 )
b11010 %
1&
#52
0&
#53
b1101001000010100110010 4
b1111011111110111001110 3
b10000001 2
b1111101 1
b10111110101111011111110111001110 !
b10111110101111011111110111001110 (
b11000000101101001000010100110010 "
b11000000101101001000010100110010 )
b11011 %
1&
#54
0&
#55
b110011110101101011111110010101 $
b110011110101101011111110010101 *
b110011110101101011111110010101 0
1/
0.
0,
b1001101011111010100001 4
b10001001011110011011000 3
b10000000 1
b11000000010001001011110011011000 !
b11000000010001001011110011011000 (
b1000000101001101011111010100001 "
b1000000101001101011111010100001 )
b11100 %
1&
#56
0&
#57
b111111100000000000000000000000 $
b111111100000000000000000000000 *
b111111100000000000000000000000 0
0/
1.
1,
b10000011101110010111010 4
b1101100101000010101 3
b10000000 2
b1111111 1
b10111111100001101100101000010101 !
b10111111100001101100101000010101 (
b11000000010000011101110010111010 "
b11000000010000011101110010111010 )
b11101 %
1&
#58
0&
#59
b110011110101101011111110010101 $
b110011110101101011111110010101 *
b110011110101101011111110010101 0
1/
0.
0,
b10000101111001001100011 4
b11111110001011001110 3
b10000001 1
b11000000100011111110001011001110 !
b11000000100011111110001011001110 (
b1000000010000101111001001100011 "
b1000000010000101111001001100011 )
b11110 %
1&
#60
0&
#61
b111111100000000000000000000000 $
b111111100000000000000000000000 *
b111111100000000000000000000000 0
0/
1-
1,
0+
b11100100010000011000000 4
b11100001001000101000 3
b10000010 1
b1000001000011100001001000101000 !
b1000001000011100001001000101000 (
b11000000011100100010000011000000 "
b11000000011100100010000011000000 )
b11111 %
1&
#62
0&
#63
b1010110001011010010000 4
b101011111101101100111 3
b1111111 2
b10000001 1
b1000000100101011111101101100111 !
b1000000100101011111101101100111 (
b10111111101010110001011010010000 "
b10111111101010110001011010010000 )
b100000 %
1&
#64
0&
#65
b110011110101101011111110010101 $
b110011110101101011111110010101 *
b110011110101101011111110010101 0
1/
0-
0,
1+
b1100011111000000000111 4
b10011000111001010000 3
b10000001 2
b10000000 1
b11000000000010011000111001010000 !
b11000000000010011000111001010000 (
b1000000101100011111000000000111 "
b1000000101100011111000000000111 )
b100001 %
1&
#66
0&
#67
b111111100000000000000000000000 $
b111111100000000000000000000000 *
b111111100000000000000000000000 0
0/
1.
0+
b1010110101011111010110 4
b1000110100011111111110 3
b10000000 2
b10000001 1
b1000000101000110100011111111110 !
b1000000101000110100011111111110 (
b1000000001010110101011111010110 "
b1000000001010110101011111010110 )
b100010 %
1&
#68
0&
#69
b110011110101101011111110010101 $
b110011110101101011111110010101 *
b110011110101101011111110010101 0
1/
0.
1+
b10101000011010110001001 4
b1010010010100110111111 3
b10000001 2
b11000000101010010010100110111111 !
b11000000101010010010100110111111 (
b1000000110101000011010110001001 "
b1000000110101000011010110001001 )
b100011 %
1&
#70
0&
#71
0/
1.
0+
b11110111111001111010100 4
b1100011000011111111101 3
b10000000 2
b10000000 1
b1000000001100011000011111111101 !
b1000000001100011000011111111101 (
b1000000011110111111001111010100 "
b1000000011110111111001111010100 )
b100100 %
1&
#72
0&
#73
b11000010000000100100110 4
b1010010110100101010101 3
b1000000001010010110100101010101 !
b1000000001010010110100101010101 (
b1000000011000010000000100100110 "
b1000000011000010000000100100110 )
b100101 %
1&
#74
0&
#75
b11100011100000101010011 4
b11101001100010010001011 3
b10000001 2
b1111100 1
b111110011101001100010010001011 !
b111110011101001100010010001011 (
b1000000111100011100000101010011 "
b1000000111100011100000101010011 )
b100110 %
1&
#76
0&
#77
1,
1+
b111010100101011100100 4
b11111000011010111100011 3
b1111100 2
b10000000 1
b11000000011111000011010111100011 !
b11000000011111000011010111100011 (
b10111110000111010100101011100100 "
b10111110000111010100101011100100 )
b100111 %
1&
#78
0&
#79
b111111100000000000000000000000 $
b111111100000000000000000000000 *
b111111100000000000000000000000 0
1-
0.
0+
b11111000001101100001011 4
b11011010001011000000001 3
b10000001 2
b1111110 1
b111111011011010001011000000001 !
b111111011011010001011000000001 (
b11000000111111000001101100001011 "
b11000000111111000001101100001011 )
b101000 %
1&
#80
0&
#81
b110011110101101011111110010101 $
b110011110101101011111110010101 *
b110011110101101011111110010101 0
0-
1.
1+
b1111011100000010011000 4
b10101001110010001100000 3
b1111110 2
b10000001 1
b11000000110101001110010001100000 !
b11000000110101001110010001100000 (
b10111111001111011100000010011000 "
b10111111001111011100000010011000 )
b101001 %
1&
#82
0&
#83
0,
0+
b11111101000111011011000 4
b11110001010111010001000 3
b10000001 2
b1000000111110001010111010001000 !
b1000000111110001010111010001000 (
b1000000111111101000111011011000 "
b1000000111111101000111011011000 )
b101010 %
1&
#84
0&
#85
1,
1+
b11100011010110100011101 4
b10011000101011010001 3
b10000010 1
b11000001000010011000101011010001 !
b11000001000010011000101011010001 (
b11000000111100011010110100011101 "
b11000000111100011010110100011101 )
b101011 %
1&
#86
0&
#87
1/
0.
0,
b11110111000100110010100 4
b10111001001011010001001 3
b1111110 2
b10000001 1
b11000000110111001001011010001001 !
b11000000110111001001011010001001 (
b111111011110111000100110010100 "
b111111011110111000100110010100 )
b101100 %
1&
#88
0&
#89
b100010101010010110000 4
b11101110000101100100100 3
b10000010 2
b11000000111101110000101100100100 !
b11000000111101110000101100100100 (
b1000001000100010101010010110000 "
b1000001000100010101010010110000 )
b101101 %
1&
#90
0&
#91
b111111100000000000000000000000 $
b111111100000000000000000000000 *
b111111100000000000000000000000 0
0/
1.
0+
b1010101011111101010001 4
b1101001000111011000111 3
b10000000 2
b1000000101101001000111011000111 !
b1000000101101001000111011000111 (
b1000000001010101011111101010001 "
b1000000001010101011111101010001 )
b101110 %
1&
#92
0&
#93
b110011110101101011111110010101 $
b110011110101101011111110010101 *
b110011110101101011111110010101 0
1/
0.
1+
b10101100001000101100 4
b10011011011001010111 3
b10000010 2
b10000010 1
b11000001000010011011011001010111 !
b11000001000010011011011001010111 (
b1000001000010101100001000101100 "
b1000001000010101100001000101100 )
b101111 %
1&
#94
0&
#95
0/
1.
1,
b11101101000001011001011 4
b1011001111100111001 3
b10000001 2
b11000001000001011001111100111001 !
b11000001000001011001111100111001 (
b11000000111101101000001011001011 "
b11000000111101101000001011001011 )
b110000 %
1&
#96
0&
#97
b111111100000000000000000000000 $
b111111100000000000000000000000 *
b111111100000000000000000000000 0
b11010011100100001010 4
b1001011011111101000000 3
b10000010 2
b1111111 1
b10111111101001011011111101000000 !
b10111111101001011011111101000000 (
b11000001000011010011100100001010 "
b11000001000011010011100100001010 )
b110001 %
1&
#98
0&
#99
b110011110101101011111110010101 $
b110011110101101011111110010101 *
b110011110101101011111110010101 0
0,
0+
b10101010101100011000101 4
b101110100110111111001 3
b10000001 2
b111111100101110100110111111001 !
b111111100101110100110111111001 (
b1000000110101010101100011000101 "
b1000000110101010101100011000101 )
b110010 %
1&
#100
0&
#101
b111111100000000000000000000000 $
b111111100000000000000000000000 *
b111111100000000000000000000000 0
1-
0.
1,
b1011100010111000100111 4
b10000011111110101011001 3
b10000000 2
b10000000 1
b1000000010000011111110101011001 !
b1000000010000011111110101011001 (
b11000000001011100010111000100111 "
b11000000001011100010111000100111 )
b110011 %
1&
#102
0&
#103
b110011110101101011111110010101 $
b110011110101101011111110010101 *
b110011110101101011111110010101 0
1/
0-
0,
1+
b11011110101100111101010 4
b1101010100111001100110 3
b10000001 2
b11000000001101010100111001100110 !
b11000000001101010100111001100110 (
b1000000111011110101100111101010 "
b1000000111011110101100111101010 )
b110100 %
1&
#104
0&
#105
b111111100000000000000000000000 $
b111111100000000000000000000000 *
b111111100000000000000000000000 0
0/
1.
0+
b1100100100110001000 4
b1111011111010010001 3
b10000010 1
b1000001000001111011111010010001 !
b1000001000001111011111010010001 (
b1000000100001100100100110001000 "
b1000000100001100100100110001000 )
b110101 %
1&
#106
0&
#107
b10101010101000000000001 4
b1010010001101011111010 3
b1111100 2
b10000001 1
b1000000101010010001101011111010 !
b1000000101010010001101011111010 (
b111110010101010101000000000001 "
b111110010101010101000000000001 )
b110110 %
1&
#108
0&
#109
1-
0.
1,
b11101011000001101000001 4
b1110011011000011011110 3
b10000000 2
b1000000101110011011000011011110 !
b1000000101110011011000011011110 (
b11000000011101011000001101000001 "
b11000000011101011000001101000001 )
b110111 %
1&
#110
0&
#111
b110011110101101011111110010101 $
b110011110101101011111110010101 *
b110011110101101011111110010101 0
0-
1.
0,
b111011101011001011000 4
b1010010000000001100 3
b10000010 2
b1000000100001010010000000001100 !
b1000000100001010010000000001100 (
b1000001000111011101011001011000 "
b1000001000111011101011001011000 )
b111000 %
1&
#112
0&
#113
1/
0.
1+
b11111000000011110101111 4
b101111000101011000101 3
b10000000 2
b10000010 1
b11000001000101111000101011000101 !
b11000001000101111000101011000101 (
b1000000011111000000011110101111 "
b1000000011111000000011110101111 )
b111001 %
1&
#114
0&
#115
b111111100000000000000000000000 $
b111111100000000000000000000000 *
b111111100000000000000000000000 0
0/
1-
1,
0+
b100110110000110000111 4
b11011100001010010001100 3
b10000001 2
b1111111 1
b111111111011100001010010001100 !
b111111111011100001010010001100 (
b11000000100100110110000110000111 "
b11000000100100110110000110000111 )
b111010 %
1&
#116
0&
#117
b1000000101000001100011 4
b110101011010000100 3
b10000001 1
b1000000100000110101011010000100 !
b1000000100000110101011010000100 (
b11000000101000000101000001100011 "
b11000000101000000101000001100011 )
b111011 %
1&
#118
0&
#119
b1100101101000000100100 4
b101101110001010101101 3
b1111111 2
b10000010 1
b1000001000101101110001010101101 !
b1000001000101101110001010101101 (
b10111111101100101101000000100100 "
b10111111101100101101000000100100 )
b111100 %
1&
#120
0&
#121
0-
1.
1+
b1111100000001010110110 4
b11000101011010111000 3
b10000001 2
b10000000 1
b11000000000011000101011010111000 !
b11000000000011000101011010111000 (
b11000000101111100000001010110110 "
b11000000101111100000001010110110 )
b111101 %
1&
#122
0&
#123
b110011110101101011111110010101 $
b110011110101101011111110010101 *
b110011110101101011111110010101 0
1/
0.
0,
b11110011100100011001 4
b11101101110011100010010 3
b10000010 2
b10000001 1
b11000000111101101110011100010010 !
b11000000111101101110011100010010 (
b1000001000011110011100100011001 "
b1000001000011110011100100011001 )
b111110 %
1&
#124
0&
#125
b111111100000000000000000000000 $
b111111100000000000000000000000 *
b111111100000000000000000000000 0
0/
1.
0+
b10010110011101101110001 4
b11010001011010011010111 3
b10000001 2
b1000000111010001011010011010111 !
b1000000111010001011010011010111 (
b1000000110010110011101101110001 "
b1000000110010110011101101110001 )
b111111 %
1&
#126
0&
#127
b110011110101101011111110010101 $
b110011110101101011111110010101 *
b110011110101101011111110010101 0
1/
0.
1+
b11101111100100110001010 4
b10011001100111111100001 3
b10000000 1
b11000000010011001100111111100001 !
b11000000010011001100111111100001 (
b1000000111101111100100110001010 "
b1000000111101111100100110001010 )
b1000000 %
1&
#128
0&
#129
0/
1.
0+
b11001110111100110101101 4
b10011101010110010001110 3
b1111111 1
b111111110011101010110010001110 !
b111111110011101010110010001110 (
b1000000111001110111100110101101 "
b1000000111001110111100110101101 )
b1000001 %
1&
#130
0&
#131
b111111100000000000000000000000 $
b111111100000000000000000000000 *
b111111100000000000000000000000 0
1-
0.
1,
b11010110111000000100110 4
b1101100000101000110001 3
b1111001 2
b10000001 1
b1000000101101100000101000110001 !
b1000000101101100000101000110001 (
b10111100111010110111000000100110 "
b10111100111010110111000000100110 )
b1000010 %
1&
#132
0&
#133
b110011110101101011111110010101 $
b110011110101101011111110010101 *
b110011110101101011111110010101 0
0-
1.
0,
b100001101011110001110 4
b1010010001100000110011 3
b10000010 2
b1000000101010010001100000110011 !
b1000000101010010001100000110011 (
b1000001000100001101011110001110 "
b1000001000100001101011110001110 )
b1000011 %
1&
#134
0&
#135
1/
0.
1+
b11000001101001111100011 4
b10110100100001000101101 3
b10000001 2
b11000000110110100100001000101101 !
b11000000110110100100001000101101 (
b1000000111000001101001111100011 "
b1000000111000001101001111100011 )
b1000100 %
1&
#136
0&
#137
b111100010011100110011 4
b1001111011101000100011 3
b1111100 1
b10111110001001111011101000100011 !
b10111110001001111011101000100011 (
b1000000100111100010011100110011 "
b1000000100111100010011100110011 )
b1000101 %
1&
#138
0&
#139
b111000100000101011 4
b11111010111000011000101 3
b1111111 2
b1111110 1
b10111111011111010111000011000101 !
b10111111011111010111000011000101 (
b111111100000111000100000101011 "
b111111100000111000100000101011 )
b1000110 %
1&
#140
0&
#141
b100101111011001100010 4
b1010010011010011000010 3
b10000010 2
b10000000 1
b11000000001010010011010011000010 !
b11000000001010010011010011000010 (
b1000001000100101111011001100010 "
b1000001000100101111011001100010 )
b1000111 %
1&
#142
0&
#143
b111111100000000000000000000000 $
b111111100000000000000000000000 *
b111111100000000000000000000000 0
0/
1-
1,
0+
b11000100000001101100 4
b10011111100101111011010 3
b1111101 2
b1000000010011111100101111011010 !
b1000000010011111100101111011010 (
b10111110100011000100000001101100 "
b10111110100011000100000001101100 )
b1001000 %
1&
#144
0&
#145
b110011110101101011111110010101 $
b110011110101101011111110010101 *
b110011110101101011111110010101 0
1/
0-
0,
1+
b11000000100110110100001 4
b1010101110110000101011 3
b10000001 2
b10000001 1
b11000000101010101110110000101011 !
b11000000101010101110110000101011 (
b1000000111000000100110110100001 "
b1000000111000000100110110100001 )
b1001001 %
1&
#146
0&
#147
b111111100000000000000000000000 $
b111111100000000000000000000000 *
b111111100000000000000000000000 0
0/
1.
1,
b11011000000110110010101 4
b10100100011110000000110 3
b11000000110100100011110000000110 !
b11000000110100100011110000000110 (
b11000000111011000000110110010101 "
b11000000111011000000110110010101 )
b1001010 %
1&
#148
0&
#149
1-
0.
0+
b11101100111100001011001 4
b11011111001010001110101 3
b1000000111011111001010001110101 !
b1000000111011111001010001110101 (
b11000000111101100111100001011001 "
b11000000111101100111100001011001 )
b1001011 %
1&
#150
0&
#151
b110011110101101011111110010101 $
b110011110101101011111110010101 *
b110011110101101011111110010101 0
0-
1.
0,
b1110000101110000000011 4
b1110110111100111110110 3
b10000000 1
b1000000001110110111100111110110 !
b1000000001110110111100111110110 (
b1000000101110000101110000000011 "
b1000000101110000101110000000011 )
b1001100 %
1&
#152
0&
#153
b111111100000000000000000000000 $
b111111100000000000000000000000 *
b111111100000000000000000000000 0
1-
0.
1,
b11100111010011110000011 4
b111101100010110000001 3
b10000010 1
b1000001000111101100010110000001 !
b1000001000111101100010110000001 (
b11000000111100111010011110000011 "
b11000000111100111010011110000011 )
b1001101 %
1&
#154
0&
#155
0-
1.
0,
b10101111011111110111110 4
b11100100111110111011101 3
b1111111 2
b10000000 1
b1000000011100100111110111011101 !
b1000000011100100111110111011101 (
b111111110101111011111110111110 "
b111111110101111011111110111110 )
b1001110 %
1&
#156
0&
#157
b110011110101101011111110010101 $
b110011110101101011111110010101 *
b110011110101101011111110010101 0
1,
1+
b10111111101100000111000 4
b11001101000001101100 3
b10000010 1
b11000001000011001101000001101100 !
b11000001000011001101000001101100 (
b10111111110111111101100000111000 "
b10111111110111111101100000111000 )
b1001111 %
1&
#158
0&
#159
b111111100000000000000000000000 $
b111111100000000000000000000000 *
b111111100000000000000000000000 0
0,
0+
b11110001000001000111000 4
b101000011000000010001 3
b10000001 2
b1000001000101000011000000010001 !
b1000001000101000011000000010001 (
b1000000111110001000001000111000 "
b1000000111110001000001000111000 )
b1010000 %
1&
#160
0&
#161
b110011110101101011111110010101 $
b110011110101101011111110010101 *
b110011110101101011111110010101 0
1,
1+
b11100110010100100000111 4
b110011011011000111101 3
b10000000 2
b11000001000110011011011000111101 !
b11000001000110011011011000111101 (
b11000000011100110010100100000111 "
b11000000011100110010100100000111 )
b1010001 %
1&
#162
0&
#163
b111111100000000000000000000000 $
b111111100000000000000000000000 *
b111111100000000000000000000000 0
1-
0.
0+
b10000001100001110101000 4
b11000000010100100101100 3
b10000001 1
b1000000111000000010100100101100 !
b1000000111000000010100100101100 (
b11000000010000001100001110101000 "
b11000000010000001100001110101000 )
b1010010 %
1&
#164
0&
#165
b110011110101101011111110010101 $
b110011110101101011111110010101 *
b110011110101101011111110010101 0
1/
0-
0,
1+
b100011010110010111011 4
b10110101111111010110000 3
b10000010 2
b11000000110110101111111010110000 !
b11000000110110101111111010110000 (
b1000001000100011010110010111011 "
b1000001000100011010110010111011 )
b1010011 %
1&
#166
0&
#167
b1001111000010001001011 4
b1111111111101000110 3
b10000001 2
b10000010 1
b11000001000001111111111101000110 !
b11000001000001111111111101000110 (
b1000000101001111000010001001011 "
b1000000101001111000010001001011 )
b1010100 %
1&
#168
0&
#169
b111111100000000000000000000000 $
b111111100000000000000000000000 *
b111111100000000000000000000000 0
0/
1.
0+
b1000010100110100100111 4
b10111110110000101001010 3
b10000000 2
b10000001 1
b1000000110111110110000101001010 !
b1000000110111110110000101001010 (
b1000000001000010100110100100111 "
b1000000001000010100110100100111 )
b1010101 %
1&
#170
0&
#171
b110011110101101011111110010101 $
b110011110101101011111110010101 *
b110011110101101011111110010101 0
1,
1+
b100110101101001100000 4
b110111100010001100011 3
b10000001 2
b10000010 1
b11000001000110111100010001100011 !
b11000001000110111100010001100011 (
b11000000100100110101101001100000 "
b11000000100100110101101001100000 )
b1010110 %
1&
#172
0&
#173
b111111100000000000000000000000 $
b111111100000000000000000000000 *
b111111100000000000000000000000 0
1-
0.
0+
b1010101100011100010111 4
b10000111110101111010111 3
b10000001 1
b1000000110000111110101111010111 !
b1000000110000111110101111010111 (
b11000000101010101100011100010111 "
b11000000101010101100011100010111 )
b1010111 %
1&
#174
0&
#175
b110010111011 4
b11101101101110000010100 3
b10000010 2
b1000000111101101101110000010100 !
b1000000111101101101110000010100 (
b11000001000000000000110010111011 "
b11000001000000000000110010111011 )
b1011000 %
1&
#176
0&
#177
b110110010010001110101 4
b1010111100011101001 3
b10000010 1
b1000001000001010111100011101001 !
b1000001000001010111100011101001 (
b11000001000110110010010001110101 "
b11000001000110110010010001110101 )
b1011001 %
1&
#178
0&
#179
0-
1.
0,
b10101101111001010010101 4
b10110110110111000001011 3
b1111111 2
b10000001 1
b1000000110110110110111000001011 !
b1000000110110110110111000001011 (
b111111110101101111001010010101 "
b111111110101101111001010010101 )
b1011010 %
1&
#180
0&
#181
b110011110101101011111110010101 $
b110011110101101011111110010101 *
b110011110101101011111110010101 0
1,
1+
b11011011011010111011101 4
b111000101101010000100 3
b10000001 2
b10000010 1
b11000001000111000101101010000100 !
b11000001000111000101101010000100 (
b11000000111011011011010111011101 "
b11000000111011011011010111011101 )
b1011011 %
1&
#182
0&
#183
1/
0.
0,
b11001100001001001001001 4
b11011001001111111111111 3
b10000001 1
b11000000111011001001111111111111 !
b11000000111011001001111111111111 (
b1000000111001100001001001001001 "
b1000000111001100001001001001001 )
b1011100 %
1&
#184
0&
#185
0/
1.
1,
b1010111010110011111 4
b10010101111110001000010 3
b11000000110010101111110001000010 !
b11000000110010101111110001000010 (
b11000000100001010111010110011111 "
b11000000100001010111010110011111 )
b1011101 %
1&
#186
0&
